dicopp/base.py
dicopp/com.py
dicopp/connect.py
dicopp/daem.py
dicopp/details.py
dicopp/dload.py
dicopp/extension.py
dicopp/first.py
dicopp/flist.py
dicopp/hublist.xml.gz
dicopp/hubs.py
dicopp/hubscon.py
dicopp/hubson.py
dicopp/layout.py
dicopp/limit.py
dicopp/log.py
dicopp/main.py
dicopp/nick.py
dicopp/overrides.py
dicopp/reqs.py
dicopp/search.py
dicopp/sets.py
dicopp/share.py
dicopp/stor2.py
dicopp/userinfo.py
dicopp/users.py
dicopp/usersloc.py
dicopp-1.0.45.dist-info/METADATA
dicopp-1.0.45.dist-info/WHEEL
dicopp-1.0.45.dist-info/entry_points.txt
dicopp-1.0.45.dist-info/top_level.txt
dicopp-1.0.45.dist-info/RECORD
