Metadata-Version: 2.1
Name: dicopp
Version: 1.0.45
Summary: Direct Connect ++ client
Home-page: https://github.com/colin-i/dico
Author: cb
Author-email: costin.botescu@gmail.com
License: MIT
Requires-Python: >=3.9
Requires-Dist: PyGObject >=3.40
Requires-Dist: appdirs >=1.4.3
Requires-Dist: psutil >=5.5.1
Requires-Dist: requests >=2.21
